odoo8_addon_account_statement_operation_rule_dunning_fees-8.0.1.0.0.99.dev8-py2.7-nspkg.pth
odoo8_addon_account_statement_operation_rule_dunning_fees-8.0.1.0.0.99.dev8.dist-info/METADATA
odoo8_addon_account_statement_operation_rule_dunning_fees-8.0.1.0.0.99.dev8.dist-info/RECORD
odoo8_addon_account_statement_operation_rule_dunning_fees-8.0.1.0.0.99.dev8.dist-info/WHEEL
odoo8_addon_account_statement_operation_rule_dunning_fees-8.0.1.0.0.99.dev8.dist-info/namespace_packages.txt
odoo8_addon_account_statement_operation_rule_dunning_fees-8.0.1.0.0.99.dev8.dist-info/top_level.txt
odoo_addons/account_statement_operation_rule_dunning_fees/README.rst
odoo_addons/account_statement_operation_rule_dunning_fees/__init__.py
odoo_addons/account_statement_operation_rule_dunning_fees/__openerp__.py
odoo_addons/account_statement_operation_rule_dunning_fees/i18n/account_statement_operation_rule_dunning_fees.pot
odoo_addons/account_statement_operation_rule_dunning_fees/i18n/fr.po
odoo_addons/account_statement_operation_rule_dunning_fees/i18n/sl.po
odoo_addons/account_statement_operation_rule_dunning_fees/model/__init__.py
odoo_addons/account_statement_operation_rule_dunning_fees/model/account_statement_operation_rule.py
odoo_addons/account_statement_operation_rule_dunning_fees/static/description/icon.png
odoo_addons/account_statement_operation_rule_dunning_fees/tests/__init__.py
odoo_addons/account_statement_operation_rule_dunning_fees/tests/test_rule_dunning_fees.py
odoo_addons/account_statement_operation_rule_dunning_fees/tests/test_rule_sequence.py
odoo_addons/account_statement_operation_rule_dunning_fees/view/account_statement_operation_rule_view.xml
