Metadata-Version: 2.1
Name: odoo8-addon-account-statement-operation-rule-dunning-fees
Version: 8.0.1.0.0.99.dev8
Summary: Bank Statement Operation Rules with Dunning Fees
Home-page: http://www.camptocamp.com
Author: Camptocamp
Author-email: UNKNOWN
License: AGPL-3
Platform: UNKNOWN
Classifier: Programming Language :: Python
Classifier: Framework :: Odoo
Classifier: License :: OSI Approved :: GNU Affero General Public License v3
Requires-Python: ~=2.7
Requires-Dist: odoo8-addon-account-credit-control-dunning-fees
Requires-Dist: odoo8-addon-account-statement-operation-rule
Requires-Dist: odoo (<9.0a,>=8.0a)
